better_tinker/__init__.py
better_tinker/wrapper.py
better_tinker/bin/tinker-cli-darwin
better_tinker/bin/tinker-cli-darwin-arm64
better_tinker/bin/tinker-cli-linux
better_tinker/bin/tinker-cli-windows.exe
better_tinker/bridge/__init__.py
better_tinker/bridge/server.py
better_tinker-0.3.0.dist-info/METADATA
better_tinker-0.3.0.dist-info/WHEEL
better_tinker-0.3.0.dist-info/entry_points.txt
better_tinker-0.3.0.dist-info/RECORD
