Metadata-Version: 2.4
Name: better-tinker
Version: 0.3.0
Summary: Tinker CLI wrapper and bridge
Requires-Python: >=3.11
Requires-Dist: fastapi>=0.104.0
Requires-Dist: pydantic>=2.0.0
Requires-Dist: tinker
Requires-Dist: tinker-cookbook
Requires-Dist: uvicorn[standard]>=0.24.0
